tqe/__init__.py
tqe/main.py
tqe/embedding/transformer_emb.py
tqe/similarity/cosine_similarity.py
translation_quality_estimator-0.1.1.dist-info/LICENSE
translation_quality_estimator-0.1.1.dist-info/METADATA
translation_quality_estimator-0.1.1.dist-info/WHEEL
translation_quality_estimator-0.1.1.dist-info/top_level.txt
translation_quality_estimator-0.1.1.dist-info/RECORD
