Metadata-Version: 2.1
Name: translation-quality-estimator
Version: 0.1.1
Summary: To estimate the quality of translation
Home-page: https://github.com/theRay07/Translation-Quality-Estimator
Author: Rishav Ray
Author-email: rishavray29@gmail.com
License: MIT
Keywords: nlp bert translation quality estimator
Platform: UNKNOWN
Classifier: Topic :: Scientific/Engineering
Classifier: License :: OSI Approved :: MIT License
Classifier: Programming Language :: Python :: 3
Classifier: Programming Language :: Python :: 3.6
Classifier: Programming Language :: Python :: 3.7
Classifier: Programming Language :: Python :: 3.8
Requires-Python: >=3.6
Requires-Dist: sentence-transformers (>=0.3.8)
